mcrpy/__init__.py
mcrpy/characterize.py
mcrpy/gui_mcrpy.py
mcrpy/interpolate.py
mcrpy/match.py
mcrpy/merge.py
mcrpy/reconstruct.py
mcrpy/smooth.py
mcrpy/view.py
mcrpy/descriptors/Correlations.py
mcrpy/descriptors/CrossCorrelations.py
mcrpy/descriptors/Descriptor.py
mcrpy/descriptors/FFTCorrelations.py
mcrpy/descriptors/FFTCrossCorrelations.py
mcrpy/descriptors/GramMatrices.py
mcrpy/descriptors/LineCorrelations.py
mcrpy/descriptors/LineLinealPathApproximation.py
mcrpy/descriptors/LinealPath.py
mcrpy/descriptors/LinealPathApproximation.py
mcrpy/descriptors/MultiPhaseDescriptor.py
mcrpy/descriptors/MultiPhaseGramMatrices.py
mcrpy/descriptors/OrientationDescriptor.py
mcrpy/descriptors/PhaseDescriptor.py
mcrpy/descriptors/TwoPointCorrelations.py
mcrpy/descriptors/Variation.py
mcrpy/descriptors/VolumeFractions.py
mcrpy/descriptors/__init__.py
mcrpy/descriptors/vgg19_normalized.pkl
mcrpy/losses/L1.py
mcrpy/losses/L2.py
mcrpy/losses/Loss.py
mcrpy/losses/MSE.py
mcrpy/losses/RMS.py
mcrpy/losses/SSE.py
mcrpy/losses/__init__.py
mcrpy/optimizers/Adadelta.py
mcrpy/optimizers/Adagrad.py
mcrpy/optimizers/Adam.py
mcrpy/optimizers/Adamax.py
mcrpy/optimizers/LBFGSB.py
mcrpy/optimizers/Nadam.py
mcrpy/optimizers/Optimizer.py
mcrpy/optimizers/RMSprop.py
mcrpy/optimizers/SGD.py
mcrpy/optimizers/SPOptimizer.py
mcrpy/optimizers/SimulatedAnnealing.py
mcrpy/optimizers/TFOptimizer.py
mcrpy/optimizers/TNC.py
mcrpy/optimizers/YTPost.py
mcrpy/optimizers/__init__.py
mcrpy/src/DMCR.py
mcrpy/src/IndicatorFunction.py
mcrpy/src/Microstructure.py
mcrpy/src/MutableMicrostructure.py
mcrpy/src/Settings.py
mcrpy/src/Symmetry.py
mcrpy/src/__init__.py
mcrpy/src/descriptor_factory.py
mcrpy/src/fileutils.py
mcrpy/src/loader.py
mcrpy/src/log.py
mcrpy/src/loss_computation.py
mcrpy/src/loss_factory.py
mcrpy/src/numerical_precision.py
mcrpy/src/optimizer_factory.py
mcrpy/src/point_browser.py
mcrpy/src/profile.py
mcrpy/src/translation.py
mcrpy-0.2.0.dist-info/LICENSE
mcrpy-0.2.0.dist-info/METADATA
mcrpy-0.2.0.dist-info/WHEEL
mcrpy-0.2.0.dist-info/top_level.txt
mcrpy-0.2.0.dist-info/RECORD
